gimpey_com_sol_gateway/__init__.py
gimpey_com_sol_gateway/clients/__init__.py
gimpey_com_sol_gateway/clients/pump_fun_client.py
gimpey_com_sol_gateway/generated/__init__.py
gimpey_com_sol_gateway/generated/daos_fund_pb2.py
gimpey_com_sol_gateway/generated/daos_fund_pb2_grpc.py
gimpey_com_sol_gateway/generated/ping_pb2.py
gimpey_com_sol_gateway/generated/ping_pb2_grpc.py
gimpey_com_sol_gateway/generated/pumpfun_pb2.py
gimpey_com_sol_gateway/generated/pumpfun_pb2_grpc.py
gimpey_com_sol_gateway/generated/raydium_pb2.py
gimpey_com_sol_gateway/generated/raydium_pb2_grpc.py
gimpey_com_sol_gateway/generated/solana_pb2.py
gimpey_com_sol_gateway/generated/solana_pb2_grpc.py
gimpey_com_sol_gateway/requests/__init__.py
gimpey_com_sol_gateway-0.1.0.dist-info/METADATA
gimpey_com_sol_gateway-0.1.0.dist-info/WHEEL
gimpey_com_sol_gateway-0.1.0.dist-info/top_level.txt
gimpey_com_sol_gateway-0.1.0.dist-info/RECORD
